jupyter_openstack/__init__.py
jupyter_openstack/_version.py
jupyter_openstack/handlers.py
jupyter_openstack/tests/__init__.py
jupyter_openstack/tests/test_handlers.py
jupyter_openstack-0.0.2.data/data/etc/jupyter/jupyter_notebook_config.d/jupyter_openstack.json
jupyter_openstack-0.0.2.data/data/etc/jupyter/jupyter_server_config.d/jupyter_openstack.json
jupyter_openstack-0.0.2.data/data/share/jupyter/labextensions/@datalayer/jupyter-openstack/build_log.json
jupyter_openstack-0.0.2.data/data/share/jupyter/labextensions/@datalayer/jupyter-openstack/package.json
jupyter_openstack-0.0.2.data/data/share/jupyter/labextensions/@datalayer/jupyter-openstack/schemas/@datalayer/jupyter-admin/package.json.orig
jupyter_openstack-0.0.2.data/data/share/jupyter/labextensions/@datalayer/jupyter-openstack/schemas/@datalayer/jupyter-admin/plugin.json
jupyter_openstack-0.0.2.data/data/share/jupyter/labextensions/@datalayer/jupyter-openstack/static/lib_index_js.4348b810ae8dc12e002f.js
jupyter_openstack-0.0.2.data/data/share/jupyter/labextensions/@datalayer/jupyter-openstack/static/lib_index_js.4348b810ae8dc12e002f.js.map
jupyter_openstack-0.0.2.data/data/share/jupyter/labextensions/@datalayer/jupyter-openstack/static/remoteEntry.60045aa25abfdbe55e4f.js
jupyter_openstack-0.0.2.data/data/share/jupyter/labextensions/@datalayer/jupyter-openstack/static/remoteEntry.60045aa25abfdbe55e4f.js.map
jupyter_openstack-0.0.2.data/data/share/jupyter/labextensions/@datalayer/jupyter-openstack/static/style.js
jupyter_openstack-0.0.2.data/data/share/jupyter/labextensions/@datalayer/jupyter-openstack/static/style_index_js.09ea6e1de3ce833faf40.js
jupyter_openstack-0.0.2.data/data/share/jupyter/labextensions/@datalayer/jupyter-openstack/static/style_index_js.09ea6e1de3ce833faf40.js.map
jupyter_openstack-0.0.2.data/data/share/jupyter/labextensions/@datalayer/jupyter-openstack/static/vendors-node_modules_css-loader_dist_runtime_api_js-node_modules_css-loader_dist_runtime_cssW-72eba1.bac0ab4f283009af8f3d.js
jupyter_openstack-0.0.2.dist-info/METADATA
jupyter_openstack-0.0.2.dist-info/WHEEL
jupyter_openstack-0.0.2.dist-info/licenses/LICENSE
jupyter_openstack-0.0.2.dist-info/RECORD
